{
  "player_info": {
    "id": 662,
    "name": "T. Ndombélé",
    "firstname": "Tanguy",
    "lastname": "Ndombélé Alvaro",
    "age": 29,
    "birth": {
      "date": "1996-12-28",
      "place": "Longjumeau",
      "country": "France"
    },
    "nationality": "France",
    "height": "181 cm",
    "weight": "76 kg",
    "injured": false,
    "photo": "https://media.api-sports.io/football/players/662.png"
  },
  "team_context": {
    "team_id": 47,
    "team_name": "Tottenham",
    "season": 2020
  },
  "season_summary": {
    "season": 2020,
    "team_id": 47,
    "team_name": "Tottenham",
    "primary_position": "Midfielder",
    "total_competitions": 5,
    "key_metrics": {
      "appearances": 47,
      "goals": 6,
      "assists": 4,
      "minutes": 2877,
      "average_rating": 7.12
    }
  },
  "competition_stats": [
    {
      "league_info": {
        "id": 39,
        "name": "Premier League",
        "country": "England",
        "logo": "https://media.api-sports.io/football/leagues/39.png",
        "flag": "https://media.api-sports.io/flags/gb-eng.svg",
        "season": 2020
      },
      "team_info": {
        "id": 47,
        "name": "Tottenham",
        "logo": "https://media.api-sports.io/football/teams/47.png"
      },
      "performance_stats": {
        "appearances": 33,
        "lineups": 28,
        "minutes": 2108,
        "number": null,
        "position": "Midfielder",
        "rating": "6.887878",
        "captain": false
      },
      "scoring_stats": {
        "goals_total": 3,
        "goals_conceded": 0,
        "assists": 2,
        "saves": null
      },
      "passing_stats": {
        "passes_total": 1172,
        "passes_key": 14,
        "passes_accuracy": null
      },
      "defensive_stats": {
        "tackles_total": 41,
        "tackles_blocks": 4,
        "tackles_interceptions": 19
      },
      "duel_stats": {
        "duels_total": 313,
        "duels_won": 186
      },
      "dribbling_stats": {
        "dribbles_attempts": 99,
        "dribbles_success": 74,
        "dribbles_past": null
      },
      "discipline_stats": {
        "fouls_drawn": 61,
        "fouls_committed": 26,
        "cards_yellow": 3,
        "cards_yellowred": 0,
        "cards_red": 0
      },
      "penalty_stats": {
        "penalty_won": null,
        "penalty_committed": null,
        "penalty_scored": 0,
        "penalty_missed": 0,
        "penalty_saved": null
      },
      "shooting_stats": {
        "shots_total": 10,
        "shots_on": 7
      }
    },
    {
      "league_info": {
        "id": 48,
        "name": "League Cup",
        "country": "England",
        "logo": "https://media.api-sports.io/football/leagues/48.png",
        "flag": "https://media.api-sports.io/flags/gb-eng.svg",
        "season": 2020
      },
      "team_info": {
        "id": 47,
        "name": "Tottenham",
        "logo": "https://media.api-sports.io/football/teams/47.png"
      },
      "performance_stats": {
        "appearances": 2,
        "lineups": 2,
        "minutes": 180,
        "number": null,
        "position": "Midfielder",
        "rating": "7.150000",
        "captain": false
      },
      "scoring_stats": {
        "goals_total": 0,
        "goals_conceded": 0,
        "assists": 1,
        "saves": null
      },
      "passing_stats": {
        "passes_total": 86,
        "passes_key": 3,
        "passes_accuracy": null
      },
      "defensive_stats": {
        "tackles_total": 2,
        "tackles_blocks": null,
        "tackles_interceptions": null
      },
      "duel_stats": {
        "duels_total": 33,
        "duels_won": 18
      },
      "dribbling_stats": {
        "dribbles_attempts": 12,
        "dribbles_success": 8,
        "dribbles_past": null
      },
      "discipline_stats": {
        "fouls_drawn": 5,
        "fouls_committed": 4,
        "cards_yellow": 0,
        "cards_yellowred": 0,
        "cards_red": 0
      },
      "penalty_stats": {
        "penalty_won": null,
        "penalty_committed": null,
        "penalty_scored": 0,
        "penalty_missed": 0,
        "penalty_saved": null
      },
      "shooting_stats": {
        "shots_total": 1,
        "shots_on": null
      }
    },
    {
      "league_info": {
        "id": 45,
        "name": "FA Cup",
        "country": "England",
        "logo": "https://media.api-sports.io/football/leagues/45.png",
        "flag": "https://media.api-sports.io/flags/gb-eng.svg",
        "season": 2020
      },
      "team_info": {
        "id": 47,
        "name": "Tottenham",
        "logo": "https://media.api-sports.io/football/teams/47.png"
      },
      "performance_stats": {
        "appearances": 2,
        "lineups": 1,
        "minutes": 112,
        "number": null,
        "position": "Midfielder",
        "rating": "7.600000",
        "captain": false
      },
      "scoring_stats": {
        "goals_total": 2,
        "goals_conceded": 0,
        "assists": null,
        "saves": null
      },
      "passing_stats": {
        "passes_total": 66,
        "passes_key": 2,
        "passes_accuracy": null
      },
      "defensive_stats": {
        "tackles_total": 1,
        "tackles_blocks": null,
        "tackles_interceptions": 2
      },
      "duel_stats": {
        "duels_total": 13,
        "duels_won": 5
      },
      "dribbling_stats": {
        "dribbles_attempts": 1,
        "dribbles_success": 1,
        "dribbles_past": null
      },
      "discipline_stats": {
        "fouls_drawn": 1,
        "fouls_committed": 1,
        "cards_yellow": 0,
        "cards_yellowred": 0,
        "cards_red": 0
      },
      "penalty_stats": {
        "penalty_won": null,
        "penalty_committed": null,
        "penalty_scored": 0,
        "penalty_missed": 0,
        "penalty_saved": null
      },
      "shooting_stats": {
        "shots_total": 3,
        "shots_on": 2
      }
    },
    {
      "league_info": {
        "id": 3,
        "name": "UEFA Europa League",
        "country": "World",
        "logo": "https://media.api-sports.io/football/leagues/3.png",
        "flag": null,
        "season": 2020
      },
      "team_info": {
        "id": 47,
        "name": "Tottenham",
        "logo": "https://media.api-sports.io/football/teams/47.png"
      },
      "performance_stats": {
        "appearances": 9,
        "lineups": 4,
        "minutes": 431,
        "number": null,
        "position": "Midfielder",
        "rating": "6.842857",
        "captain": false
      },
      "scoring_stats": {
        "goals_total": 1,
        "goals_conceded": 0,
        "assists": 1,
        "saves": null
      },
      "passing_stats": {
        "passes_total": 252,
        "passes_key": 2,
        "passes_accuracy": null
      },
      "defensive_stats": {
        "tackles_total": 14,
        "tackles_blocks": null,
        "tackles_interceptions": 1
      },
      "duel_stats": {
        "duels_total": 58,
        "duels_won": 34
      },
      "dribbling_stats": {
        "dribbles_attempts": 21,
        "dribbles_success": 11,
        "dribbles_past": null
      },
      "discipline_stats": {
        "fouls_drawn": 9,
        "fouls_committed": 6,
        "cards_yellow": 1,
        "cards_yellowred": 0,
        "cards_red": 0
      },
      "penalty_stats": {
        "penalty_won": null,
        "penalty_committed": null,
        "penalty_scored": 0,
        "penalty_missed": 0,
        "penalty_saved": null
      },
      "shooting_stats": {
        "shots_total": 2,
        "shots_on": 1
      }
    },
    {
      "league_info": {
        "id": 667,
        "name": "Friendlies Clubs",
        "country": "World",
        "logo": "https://media.api-sports.io/football/leagues/667.png",
        "flag": null,
        "season": 2020
      },
      "team_info": {
        "id": 47,
        "name": "Tottenham",
        "logo": "https://media.api-sports.io/football/teams/47.png"
      },
      "performance_stats": {
        "appearances": 1,
        "lineups": 1,
        "minutes": 46,
        "number": null,
        "position": "Midfielder",
        "rating": null,
        "captain": false
      },
      "scoring_stats": {
        "goals_total": 0,
        "goals_conceded": null,
        "assists": null,
        "saves": null
      },
      "passing_stats": {
        "passes_total": null,
        "passes_key": null,
        "passes_accuracy": null
      },
      "defensive_stats": {
        "tackles_total": null,
        "tackles_blocks": null,
        "tackles_interceptions": null
      },
      "duel_stats": {
        "duels_total": null,
        "duels_won": null
      },
      "dribbling_stats": {
        "dribbles_attempts": null,
        "dribbles_success": null,
        "dribbles_past": null
      },
      "discipline_stats": {
        "fouls_drawn": null,
        "fouls_committed": null,
        "cards_yellow": 0,
        "cards_yellowred": 0,
        "cards_red": 0
      },
      "penalty_stats": {
        "penalty_won": null,
        "penalty_committed": null,
        "penalty_scored": null,
        "penalty_missed": null,
        "penalty_saved": null
      },
      "shooting_stats": {
        "shots_total": null,
        "shots_on": null
      }
    }
  ],
  "aggregated_stats": {
    "total_appearances": 47,
    "total_lineups": 36,
    "total_minutes": 2877,
    "total_goals": 6,
    "total_assists": 4,
    "total_yellow_cards": 4,
    "total_red_cards": 0,
    "competitions_played": 5,
    "average_rating": 7.12,
    "goals_per_90": 0.19,
    "assists_per_90": 0.13,
    "minutes_per_appearance": 61.2
  },
  "metadata": {
    "file_created": "2025-07-03T12:14:04.984064",
    "source_file": "team_47_players_2020.json",
    "data_structure_version": "1.0"
  }
}